napari_solarized/__init__.py
napari_solarized/_version.py
napari_solarized/napari.yaml
napari_solarized-0.1.1.dist-info/LICENSE
napari_solarized-0.1.1.dist-info/METADATA
napari_solarized-0.1.1.dist-info/WHEEL
napari_solarized-0.1.1.dist-info/entry_points.txt
napari_solarized-0.1.1.dist-info/top_level.txt
napari_solarized-0.1.1.dist-info/RECORD
