Metadata-Version: 2.1
Name: napari-solarized
Version: 0.1.1
Summary: Solarized themes for napari
Home-page: https://github.com/aganders3/napari-solarized
Author: Ashley Anderson
Author-email: aandersoniii@chanzuckerberg.com
License: MIT
Project-URL: Bug Tracker, https://github.com/aganders3/napari-solarized/issues
Project-URL: Documentation, https://github.com/aganders3/napari-solarized#README.md
Project-URL: Source Code, https://github.com/aganders3/napari-solarized
Project-URL: User Support, https://github.com/aganders3/napari-solarized/issues
Classifier: Development Status :: 2 - Pre-Alpha
Classifier: Framework :: napari
Classifier: Intended Audience :: Developers
Classifier: License :: OSI Approved :: Mozilla Public License 2.0 (MPL 2.0)
Classifier: Operating System :: OS Independent
Classifier: Programming Language :: Python
Classifier: Programming Language :: Python :: 3
Classifier: Programming Language :: Python :: 3 :: Only
Classifier: Programming Language :: Python :: 3.8
Classifier: Programming Language :: Python :: 3.9
Classifier: Programming Language :: Python :: 3.10
Classifier: Topic :: Scientific/Engineering :: Image Processing
Requires-Python: >=3.8
License-File: LICENSE
Provides-Extra: testing
Requires-Dist: pytest ; extra == 'testing'
Requires-Dist: pytest-cov ; extra == 'testing'
Requires-Dist: npe2 ; extra == 'testing'
Requires-Dist: typer ; extra == 'testing'
Requires-Dist: importlib-resources ; extra == 'testing'
